{"metadata":{"formatVersion":{"major":0,"minor":6,"patch":0},"generator":"Swift version 5.8-dev (LLVM c44b030a65f0a4d, Swift fb9ecb25924353e)"},"module":{"name":"D","platform":{"architecture":"arm64","vendor":"apple","operatingSystem":{"name":"macosx","minimumVersion":{"major":10,"minor":10,"patch":0}}}},"symbols":[{"kind":{"identifier":"swift.method","displayName":"Instance Method"},"identifier":{"precise":"s:1A9AProtocolP1DE4dbarSdyF","interfaceLanguage":"swift"},"pathComponents":["AProtocol","dbar()"],"names":{"title":"dbar()","subHeading":[{"kind":"keyword","spelling":"func"},{"kind":"text","spelling":" "},{"kind":"identifier","spelling":"dbar"},{"kind":"text","spelling":"() -> "},{"kind":"typeIdentifier","spelling":"Double","preciseIdentifier":"s:Sd"}]},"functionSignature":{"returns":[{"kind":"typeIdentifier","spelling":"Double","preciseIdentifier":"s:Sd"}]},"swiftExtension":{"extendedModule":"A","typeKind":"protocol"},"declarationFragments":[{"kind":"keyword","spelling":"func"},{"kind":"text","spelling":" "},{"kind":"identifier","spelling":"dbar"},{"kind":"text","spelling":"() -> "},{"kind":"typeIdentifier","spelling":"Double","preciseIdentifier":"s:Sd"}],"accessLevel":"public","location":{"uri":"file:///Users/themomax/Development/github.com/themomax/SampleSymbolGraphProject/D/Sources/D/D.swift","position":{"line":8,"character":9}}},{"kind":{"identifier":"swift.struct","displayName":"Structure"},"identifier":{"precise":"s:1A7AStructV1BE7BStructV1CE7CStructV1DE7DStructV","interfaceLanguage":"swift"},"pathComponents":["AStruct","BStruct","CStruct","DStruct"],"names":{"title":"AStruct.BStruct.CStruct.DStruct","navigator":[{"kind":"identifier","spelling":"DStruct"}],"subHeading":[{"kind":"keyword","spelling":"struct"},{"kind":"text","spelling":" "},{"kind":"identifier","spelling":"DStruct"}]},"swiftExtension":{"extendedModule":"C","typeKind":"struct"},"declarationFragments":[{"kind":"keyword","spelling":"struct"},{"kind":"text","spelling":" "},{"kind":"identifier","spelling":"DStruct"}],"accessLevel":"public","location":{"uri":"file:///Users/themomax/Development/github.com/themomax/SampleSymbolGraphProject/D/Sources/D/D.swift","position":{"line":34,"character":11}}},{"kind":{"identifier":"swift.extension","displayName":"Extension"},"identifier":{"precise":"s:e:s:1A7AStructV1BE7BStructV1CE7CStructV1DE7DStructV","interfaceLanguage":"swift"},"pathComponents":["AStruct","BStruct","CStruct"],"names":{"title":"AStruct.BStruct.CStruct","navigator":[{"kind":"identifier","spelling":"CStruct"}],"subHeading":[{"kind":"keyword","spelling":"extension"},{"kind":"text","spelling":" "},{"kind":"typeIdentifier","spelling":"AStruct","preciseIdentifier":"s:1A7AStructV"},{"kind":"text","spelling":"."},{"kind":"typeIdentifier","spelling":"BStruct","preciseIdentifier":"s:1A7AStructV1BE7BStructV"},{"kind":"text","spelling":"."},{"kind":"typeIdentifier","spelling":"CStruct","preciseIdentifier":"s:1A7AStructV1BE7BStructV1CE7CStructV"}]},"swiftExtension":{"extendedModule":"C","typeKind":"struct"},"declarationFragments":[{"kind":"keyword","spelling":"extension"},{"kind":"text","spelling":" "},{"kind":"typeIdentifier","spelling":"AStruct","preciseIdentifier":"s:1A7AStructV"},{"kind":"text","spelling":"."},{"kind":"typeIdentifier","spelling":"BStruct","preciseIdentifier":"s:1A7AStructV1BE7BStructV"},{"kind":"text","spelling":"."},{"kind":"typeIdentifier","spelling":"CStruct","preciseIdentifier":"s:1A7AStructV1BE7BStructV1CE7CStructV"}],"accessLevel":"public","location":{"uri":"file:///Users/themomax/Development/github.com/themomax/SampleSymbolGraphProject/D/Sources/D/D.swift","position":{"line":33,"character":7}}},{"kind":{"identifier":"swift.extension","displayName":"Extension"},"identifier":{"precise":"s:e:s:1A9AProtocolP1DE4dbarSiyF","interfaceLanguage":"swift"},"pathComponents":["AProtocol"],"names":{"title":"AProtocol","navigator":[{"kind":"identifier","spelling":"AProtocol"}],"subHeading":[{"kind":"keyword","spelling":"extension"},{"kind":"text","spelling":" "},{"kind":"typeIdentifier","spelling":"AProto","preciseIdentifier":"s:1A6AProtoa"}]},"swiftGenerics":{"constraints":[{"kind":"conformance","lhs":"Self","rhs":"AProtocol","rhsPrecise":"s:1A9AProtocolP"}]},"swiftExtension":{"extendedModule":"A","typeKind":"protocol"},"declarationFragments":[{"kind":"keyword","spelling":"extension"},{"kind":"text","spelling":" "},{"kind":"typeIdentifier","spelling":"AProto","preciseIdentifier":"s:1A6AProtoa"}],"accessLevel":"public","location":{"uri":"file:///Users/themomax/Development/github.com/themomax/SampleSymbolGraphProject/D/Sources/D/D.swift","position":{"line":12,"character":7}}},{"kind":{"identifier":"swift.method","displayName":"Instance Method"},"identifier":{"precise":"s:1A9AProtocolP1DE4dbarSiyF","interfaceLanguage":"swift"},"pathComponents":["AProtocol","dbar()"],"names":{"title":"dbar()","subHeading":[{"kind":"keyword","spelling":"func"},{"kind":"text","spelling":" "},{"kind":"identifier","spelling":"dbar"},{"kind":"text","spelling":"() -> "},{"kind":"typeIdentifier","spelling":"Int","preciseIdentifier":"s:Si"}]},"functionSignature":{"returns":[{"kind":"typeIdentifier","spelling":"Int","preciseIdentifier":"s:Si"}]},"swiftExtension":{"extendedModule":"A","typeKind":"protocol"},"declarationFragments":[{"kind":"keyword","spelling":"func"},{"kind":"text","spelling":" "},{"kind":"identifier","spelling":"dbar"},{"kind":"text","spelling":"() -> "},{"kind":"typeIdentifier","spelling":"Int","preciseIdentifier":"s:Si"}],"accessLevel":"public","location":{"uri":"file:///Users/themomax/Development/github.com/themomax/SampleSymbolGraphProject/D/Sources/D/D.swift","position":{"line":13,"character":9}}},{"kind":{"identifier":"swift.extension","displayName":"Extension"},"identifier":{"precise":"s:e:s:1A9AProtocolP1DE4dbarSdyF","interfaceLanguage":"swift"},"pathComponents":["AProtocol"],"names":{"title":"AProtocol","navigator":[{"kind":"identifier","spelling":"AProtocol"}],"subHeading":[{"kind":"keyword","spelling":"extension"},{"kind":"text","spelling":" "},{"kind":"typeIdentifier","spelling":"AProtocol","preciseIdentifier":"s:1A9AProtocolP"}]},"swiftGenerics":{"constraints":[{"kind":"conformance","lhs":"Self","rhs":"AProtocol","rhsPrecise":"s:1A9AProtocolP"}]},"swiftExtension":{"extendedModule":"A","typeKind":"protocol"},"declarationFragments":[{"kind":"keyword","spelling":"extension"},{"kind":"text","spelling":" "},{"kind":"typeIdentifier","spelling":"AProtocol","preciseIdentifier":"s:1A9AProtocolP"}],"accessLevel":"public","location":{"uri":"file:///Users/themomax/Development/github.com/themomax/SampleSymbolGraphProject/D/Sources/D/D.swift","position":{"line":7,"character":7}}}],"relationships":[{"kind":"memberOf","source":"s:1A9AProtocolP1DE4dbarSdyF","target":"s:e:s:1A9AProtocolP1DE4dbarSdyF","targetFallback":"A.AProtocol"},{"kind":"memberOf","source":"s:1A7AStructV1BE7BStructV1CE7CStructV1DE7DStructV","target":"s:e:s:1A7AStructV1BE7BStructV1CE7CStructV1DE7DStructV","targetFallback":"C.AStruct.BStruct.CStruct"},{"kind":"extensionTo","source":"s:e:s:1A7AStructV1BE7BStructV1CE7CStructV1DE7DStructV","target":"s:1A7AStructV1BE7BStructV1CE7CStructV","targetFallback":"C.AStruct.BStruct.CStruct"},{"kind":"extensionTo","source":"s:e:s:1A9AProtocolP1DE4dbarSiyF","target":"s:1A9AProtocolP","targetFallback":"A.AProtocol"},{"kind":"extensionTo","source":"s:e:s:1A9AProtocolP1DE4dbarSdyF","target":"s:1A9AProtocolP","targetFallback":"A.AProtocol"},{"kind":"memberOf","source":"s:1A9AProtocolP1DE4dbarSiyF","target":"s:e:s:1A9AProtocolP1DE4dbarSiyF","targetFallback":"A.AProtocol"}]}